worldmap/__init__.py
worldmap/examples.py
worldmap/worldmap.py
worldmap/data/__init__.py
worldmap/utils/__init__.py
worldmap/utils/deepStringMatching.py
worldmap/utils/stringPreprocessing.py
worldmap/utils/strtricks.py
worldmap/utils/zip_extract.py
worldmap-0.1.7.dist-info/LICENSE
worldmap-0.1.7.dist-info/METADATA
worldmap-0.1.7.dist-info/WHEEL
worldmap-0.1.7.dist-info/top_level.txt
worldmap-0.1.7.dist-info/RECORD
