Metadata-Version: 2.1
Name: worldmap
Version: 0.1.7
Summary: worldmap is to plot and color countries or specific regions in a country using offline approaches.
Home-page: https://erdogant.github.io/worldmap
Download-URL: https://github.com/erdogant/worldmap/archive/0.1.7.tar.gz
Author: Erdogan Taskesen
Author-email: erdogant@gmail.com
Classifier: Programming Language :: Python :: 3
Classifier: License :: OSI Approved :: MIT License
Classifier: Operating System :: OS Independent
Requires-Python: >=3
License-File: LICENSE
Requires-Dist: wget
Requires-Dist: matplotlib
Requires-Dist: numpy
Requires-Dist: pandas
Requires-Dist: svgpathtools
Requires-Dist: colourmap
Requires-Dist: tqdm
Requires-Dist: rapidfuzz
Requires-Dist: scikit-learn
Requires-Dist: seaborn
